lmu_meteo_api/__init__.py
lmu_meteo_api/interface.py
lmu_meteo_api-0.2.1.dist-info/WHEEL
lmu_meteo_api-0.2.1.dist-info/METADATA
lmu_meteo_api-0.2.1.dist-info/RECORD
