Metadata-Version: 2.1
Name: lmu-meteo-api
Version: 0.2.1
Summary: Python interface to request data from the LMU Meteorology station.
Author: DanielKuebi
Author-email: daniflug95@live.at
Requires-Python: >=3.10,<4.0
Classifier: Programming Language :: Python :: 3
Classifier: Programming Language :: Python :: 3.10
Classifier: Programming Language :: Python :: 3.11
Requires-Dist: numpy (>=1.25.2,<2.0.0)
Requires-Dist: pandas (>=2.1.0,<3.0.0)
Requires-Dist: requests (>=2.31.0,<3.0.0)
